MLStructFP/__init__.py
MLStructFP/_types.py
MLStructFP/db/__init__.py
MLStructFP/db/_c.py
MLStructFP/db/_c_item.py
MLStructFP/db/_c_point.py
MLStructFP/db/_c_rect.py
MLStructFP/db/_c_room.py
MLStructFP/db/_c_slab.py
MLStructFP/db/_db_loader.py
MLStructFP/db/_floor.py
MLStructFP/db/image/__init__.py
MLStructFP/db/image/_base.py
MLStructFP/db/image/_rect_binary.py
MLStructFP/db/image/_rect_photo.py
MLStructFP/utils/__init__.py
MLStructFP/utils/_geometry.py
MLStructFP/utils/_mathlib.py
MLStructFP/utils/_path.py
MLStructFP/utils/_plot.py
mlstructfp-0.7.4.dist-info/LICENSE
mlstructfp-0.7.4.dist-info/METADATA
mlstructfp-0.7.4.dist-info/WHEEL
mlstructfp-0.7.4.dist-info/top_level.txt
mlstructfp-0.7.4.dist-info/RECORD
