Metadata-Version: 2.1
Name: mlstructfp
Version: 0.7.4
Summary: Machine learning structural floor plan dataset
Home-page: https://github.com/MLSTRUCT/MLSTRUCT-FP
Author: Pablo Pizarro R.
Author-email: pablo@ppizarror.com
Project-URL: Bug Tracker, https://github.com/MLSTRUCT/MLSTRUCT-FP/issues
Project-URL: Documentation, https://github.com/MLSTRUCT/MLSTRUCT-FP
Project-URL: Source Code, https://github.com/MLSTRUCT/MLSTRUCT-FP
Keywords: ml,ai,floor plan,architectural,dataset,cnn
Platform: any
Classifier: Natural Language :: English
Classifier: Operating System :: OS Independent
Classifier: Programming Language :: Python :: 3.8
Classifier: Programming Language :: Python
Classifier: Topic :: Scientific/Engineering
Classifier: Topic :: Scientific/Engineering :: Artificial Intelligence
Classifier: Topic :: Scientific/Engineering :: Image Recognition
Classifier: Topic :: Scientific/Engineering :: Visualization
Requires-Python: >=3.8
License-File: LICENSE
Requires-Dist: IPython>=8.12.3
Requires-Dist: matplotlib>=3.5.3
Requires-Dist: numpy>=1.18.5
Requires-Dist: opencv-python<=4.5.4.60
Requires-Dist: Pillow>=10.4.0
Requires-Dist: plotly>=5.24.1
Requires-Dist: requests>=2.32.3
Requires-Dist: tabulate>=0.9.0
Provides-Extra: test
Requires-Dist: nose2[coverage_plugin]; extra == "test"
Requires-Dist: pytest; extra == "test"
